README.txt
setup.cfg
setup.py
mio/__init__.py
mio/reader/__init__.py
mio/reader/tmxml/__init__.py
mio/reader/tmxml/handler.py
tm.reader.tmxml.egg-info/PKG-INFO
tm.reader.tmxml.egg-info/SOURCES.txt
tm.reader.tmxml.egg-info/dependency_links.txt
tm.reader.tmxml.egg-info/entry_points.txt
tm.reader.tmxml.egg-info/namespace_packages.txt
tm.reader.tmxml.egg-info/not-zip-safe
tm.reader.tmxml.egg-info/requires.txt
tm.reader.tmxml.egg-info/top_level.txt