Metadata-Version: 1.0
Name: tm.reader.tmxml
Version: 0.1.0
Summary: TM/XML syntax reader
Home-page: http://mappa.semagia.com/
Author: Lars Heuer
Author-email: mappa@googlegroups.com
License: BSD
Keywords: Topic Maps,Semantic Web,TMXML
Platform: any
Classifier: Intended Audience :: Developers
Classifier: Intended Audience :: Information Technology
Classifier: Topic :: Software Development
Classifier: Topic :: Software Development :: Libraries
Classifier: Topic :: Software Development :: Libraries :: Python Modules
Classifier: License :: OSI Approved :: BSD License
Classifier: Operating System :: OS Independent
Classifier: Programming Language :: Python
